{
  "industry": [
    "Games & Gaming",
    "Board Game"
  ],
  "display_term": "GnoChess",
  "term": "GnoChess",
  "tags": [
    "NFT",
    "Interactive",
    "NFT Collections"
  ],
  "glossaries": [],
  "short_description": "GnoChess is an online chess server implementation with Gno.",
  "partnerships": [],
  "author": "builtongno",
  "social": {
    "website": "https://gnochess.com/",
    "x-twitter": "https://twitter.com/_gnoland",
    "github": "https://github.com/gnolang/gnochess",
    "discord": "https://discord.com/invite/S8nKUqwkPn"
  }
}